{
    "waypointId": "contacts/android/ringtone-picker",
    "capturedAt": "2026-07-14T14:43:42.840428Z",
    "capturedFrom": "logs/2026_07_14_10_43_24_yaml_9313/004_TrailblazeLlmRequestLog.json",
    "screenshotFile": "contacts_android_ringtone_picker.example.webp",
    "deviceWidth": 1440,
    "deviceHeight": 2560,
    "trailblazeDeviceInfo": {
        "trailblazeDeviceId": {
            "instanceId": "emulator-5600",
            "trailblazeDevicePlatform": "ANDROID"
        },
        "trailblazeDriverType": "ANDROID_ONDEVICE_ACCESSIBILITY",
        "widthPixels": 1080,
        "heightPixels": 2400
    },
    "viewHierarchy": {
        "x1": 160,
        "y1": 84,
        "x2": 1280,
        "y2": 2392,
        "centerPoint": "720,1238",
        "children": [
            {
                "nodeId": 2,
                "x1": 216,
                "y1": 140,
                "x2": 1224,
                "y2": 2336,
                "centerPoint": "720,1238",
                "children": [
                    {
                        "nodeId": 3,
                        "x1": 216,
                        "y1": 140,
                        "x2": 1224,
                        "y2": 2336,
                        "centerPoint": "720,1238",
                        "children": [
                            {
                                "nodeId": 4,
                                "x1": 216,
                                "y1": 140,
                                "x2": 1224,
                                "y2": 2336,
                                "centerPoint": "720,1238",
                                "children": [
                                    {
                                        "nodeId": 5,
                                        "x1": 216,
                                        "y1": 140,
                                        "x2": 1224,
                                        "y2": 324,
                                        "centerPoint": "720,232",
                                        "children": [
                                            {
                                                "nodeId": 6,
                                                "x1": 216,
                                                "y1": 140,
                                                "x2": 1224,
                                                "y2": 296,
                                                "centerPoint": "720,218",
                                                "children": [
                                                    {
                                                        "nodeId": 7,
                                                        "x1": 300,
                                                        "y1": 203,
                                                        "x2": 1140,
                                                        "y2": 296,
                                                        "centerPoint": "720,249",
                                                        "className": "android.widget.TextView",
                                                        "resourceId": "android:id/alertTitle",
                                                        "text": "Ringtones"
                                                    }
                                                ],
                                                "className": "android.widget.LinearLayout",
                                                "resourceId": "android:id/title_template"
                                            },
                                            {
                                                "nodeId": 8,
                                                "x1": 216,
                                                "y1": 296,
                                                "x2": 1224,
                                                "y2": 324,
                                                "centerPoint": "720,310",
                                                "className": "android.view.View",
                                                "resourceId": "android:id/titleDividerNoCustom"
                                            }
                                        ],
                                        "className": "android.widget.LinearLayout",
                                        "resourceId": "android:id/topPanel"
                                    },
                                    {
                                        "nodeId": 9,
                                        "x1": 216,
                                        "y1": 324,
                                        "x2": 1224,
                                        "y2": 2140,
                                        "centerPoint": "720,1232",
                                        "children": [
                                            {
                                                "nodeId": 10,
                                                "x1": 216,
                                                "y1": 324,
                                                "x2": 1224,
                                                "y2": 2140,
                                                "centerPoint": "720,1232",
                                                "children": [
                                                    {
                                                        "nodeId": 11,
                                                        "x1": 216,
                                                        "y1": 324,
                                                        "x2": 1224,
                                                        "y2": 492,
                                                        "centerPoint": "720,408",
                                                        "checked": true,
                                                        "className": "android.widget.CheckedTextView",
                                                        "clickable": true,
                                                        "resourceId": "android:id/text1",
                                                        "text": "Default ringtone"
                                                    },
                                                    {
                                                        "nodeId": 12,
                                                        "x1": 216,
                                                        "y1": 492,
                                                        "x2": 1224,
                                                        "y2": 660,
                                                        "centerPoint": "720,576",
                                                        "className": "android.widget.CheckedTextView",
                                                        "clickable": true,
                                                        "resourceId": "android:id/text1",
                                                        "text": "None"
                                                    },
                                                    {
                                                        "nodeId": 13,
                                                        "x1": 216,
                                                        "y1": 660,
                                                        "x2": 1224,
                                                        "y2": 828,
                                                        "centerPoint": "720,744",
                                                        "children": [
                                                            {
                                                                "nodeId": 14,
                                                                "x1": 216,
                                                                "y1": 660,
                                                                "x2": 1224,
                                                                "y2": 828,
                                                                "centerPoint": "720,744",
                                                                "className": "android.widget.CheckedTextView",
                                                                "resourceId": "com.android.soundpicker:id/checked_text_view",
                                                                "text": "Andromeda"
                                                            }
                                                        ],
                                                        "className": "android.widget.RelativeLayout",
                                                        "clickable": true
                                                    },
                                                    {
                                                        "nodeId": 15,
                                                        "x1": 216,
                                                        "y1": 828,
                                                        "x2": 1224,
                                                        "y2": 996,
                                                        "centerPoint": "720,912",
                                                        "children": [
                                                            {
                                                                "nodeId": 16,
                                                                "x1": 216,
                                                                "y1": 828,
                                                                "x2": 1224,
                                                                "y2": 996,
                                                                "centerPoint": "720,912",
                                                                "className": "android.widget.CheckedTextView",
                                                                "resourceId": "com.android.soundpicker:id/checked_text_view",
                                                                "text": "Aquila"
                                                            }
                                                        ],
                                                        "className": "android.widget.RelativeLayout",
                                                        "clickable": true
                                                    },
                                                    {
                                                        "nodeId": 17,
                                                        "x1": 216,
                                                        "y1": 996,
                                                        "x2": 1224,
                                                        "y2": 1164,
                                                        "centerPoint": "720,1080",
                                                        "children": [
                                                            {
                                                                "nodeId": 18,
                                                                "x1": 216,
                                                                "y1": 996,
                                                                "x2": 1224,
                                                                "y2": 1164,
                                                                "centerPoint": "720,1080",
                                                                "className": "android.widget.CheckedTextView",
                                                                "resourceId": "com.android.soundpicker:id/checked_text_view",
                                                                "text": "Argo Navis"
                                                            }
                                                        ],
                                                        "className": "android.widget.RelativeLayout",
                                                        "clickable": true
                                                    },
                                                    {
                                                        "nodeId": 19,
                                                        "x1": 216,
                                                        "y1": 1164,
                                                        "x2": 1224,
                                                        "y2": 1332,
                                                        "centerPoint": "720,1248",
                                                        "children": [
                                                            {
                                                                "nodeId": 20,
                                                                "x1": 216,
                                                                "y1": 1164,
                                                                "x2": 1224,
                                                                "y2": 1332,
                                                                "centerPoint": "720,1248",
                                                                "className": "android.widget.CheckedTextView",
                                                                "resourceId": "com.android.soundpicker:id/checked_text_view",
                                                                "text": "Atria"
                                                            }
                                                        ],
                                                        "className": "android.widget.RelativeLayout",
                                                        "clickable": true
                                                    },
                                                    {
                                                        "nodeId": 21,
                                                        "x1": 216,
                                                        "y1": 1332,
                                                        "x2": 1224,
                                                        "y2": 1500,
                                                        "centerPoint": "720,1416",
                                                        "children": [
                                                            {
                                                                "nodeId": 22,
                                                                "x1": 216,
                                                                "y1": 1332,
                                                                "x2": 1224,
                                                                "y2": 1500,
                                                                "centerPoint": "720,1416",
                                                                "className": "android.widget.CheckedTextView",
                                                                "resourceId": "com.android.soundpicker:id/checked_text_view",
                                                                "text": "Backroad"
                                                            }
                                                        ],
                                                        "className": "android.widget.RelativeLayout",
                                                        "clickable": true
                                                    },
                                                    {
                                                        "nodeId": 23,
                                                        "x1": 216,
                                                        "y1": 1500,
                                                        "x2": 1224,
                                                        "y2": 1668,
                                                        "centerPoint": "720,1584",
                                                        "children": [
                                                            {
                                                                "nodeId": 24,
                                                                "x1": 216,
                                                                "y1": 1500,
                                                                "x2": 1224,
                                                                "y2": 1668,
                                                                "centerPoint": "720,1584",
                                                                "className": "android.widget.CheckedTextView",
                                                                "resourceId": "com.android.soundpicker:id/checked_text_view",
                                                                "text": "Beat Plucker"
                                                            }
                                                        ],
                                                        "className": "android.widget.RelativeLayout",
                                                        "clickable": true
                                                    },
                                                    {
                                                        "nodeId": 25,
                                                        "x1": 216,
                                                        "y1": 1668,
                                                        "x2": 1224,
                                                        "y2": 1836,
                                                        "centerPoint": "720,1752",
                                                        "children": [
                                                            {
                                                                "nodeId": 26,
                                                                "x1": 216,
                                                                "y1": 1668,
                                                                "x2": 1224,
                                                                "y2": 1836,
                                                                "centerPoint": "720,1752",
                                                                "className": "android.widget.CheckedTextView",
                                                                "resourceId": "com.android.soundpicker:id/checked_text_view",
                                                                "text": "Bell Phone"
                                                            }
                                                        ],
                                                        "className": "android.widget.RelativeLayout",
                                                        "clickable": true
                                                    },
                                                    {
                                                        "nodeId": 27,
                                                        "x1": 216,
                                                        "y1": 1836,
                                                        "x2": 1224,
                                                        "y2": 2004,
                                                        "centerPoint": "720,1920",
                                                        "children": [
                                                            {
                                                                "nodeId": 28,
                                                                "x1": 216,
                                                                "y1": 1836,
                                                                "x2": 1224,
                                                                "y2": 2004,
                                                                "centerPoint": "720,1920",
                                                                "className": "android.widget.CheckedTextView",
                                                                "resourceId": "com.android.soundpicker:id/checked_text_view",
                                                                "text": "Bentley Dubs"
                                                            }
                                                        ],
                                                        "className": "android.widget.RelativeLayout",
                                                        "clickable": true
                                                    },
                                                    {
                                                        "nodeId": 29,
                                                        "x1": 216,
                                                        "y1": 2004,
                                                        "x2": 1224,
                                                        "y2": 2140,
                                                        "centerPoint": "720,2072",
                                                        "children": [
                                                            {
                                                                "nodeId": 30,
                                                                "x1": 216,
                                                                "y1": 2004,
                                                                "x2": 1224,
                                                                "y2": 2140,
                                                                "centerPoint": "720,2072",
                                                                "className": "android.widget.CheckedTextView",
                                                                "resourceId": "com.android.soundpicker:id/checked_text_view",
                                                                "text": "Big Easy"
                                                            }
                                                        ],
                                                        "className": "android.widget.RelativeLayout",
                                                        "clickable": true
                                                    }
                                                ],
                                                "className": "android.widget.ListView",
                                                "focused": true,
                                                "resourceId": "android:id/select_dialog_listview",
                                                "scrollable": true
                                            }
                                        ],
                                        "className": "android.widget.FrameLayout",
                                        "resourceId": "android:id/contentPanel"
                                    },
                                    {
                                        "nodeId": 31,
                                        "x1": 216,
                                        "y1": 2140,
                                        "x2": 1224,
                                        "y2": 2336,
                                        "centerPoint": "720,2238",
                                        "children": [
                                            {
                                                "nodeId": 32,
                                                "x1": 216,
                                                "y1": 2140,
                                                "x2": 1224,
                                                "y2": 2336,
                                                "centerPoint": "720,2238",
                                                "children": [
                                                    {
                                                        "nodeId": 33,
                                                        "x1": 689,
                                                        "y1": 2154,
                                                        "x2": 958,
                                                        "y2": 2322,
                                                        "centerPoint": "823,2238",
                                                        "className": "android.widget.Button",
                                                        "clickable": true,
                                                        "resourceId": "android:id/button2",
                                                        "text": "CANCEL"
                                                    },
                                                    {
                                                        "nodeId": 34,
                                                        "x1": 958,
                                                        "y1": 2154,
                                                        "x2": 1182,
                                                        "y2": 2322,
                                                        "centerPoint": "1070,2238",
                                                        "className": "android.widget.Button",
                                                        "clickable": true,
                                                        "resourceId": "android:id/button1",
                                                        "text": "OK"
                                                    }
                                                ],
                                                "className": "android.widget.LinearLayout"
                                            }
                                        ],
                                        "className": "android.widget.ScrollView",
                                        "resourceId": "android:id/buttonPanel"
                                    }
                                ],
                                "className": "android.widget.LinearLayout",
                                "resourceId": "android:id/parentPanel"
                            }
                        ],
                        "className": "android.widget.FrameLayout",
                        "resourceId": "android:id/content"
                    }
                ],
                "className": "android.widget.FrameLayout"
            }
        ],
        "className": "android.widget.FrameLayout"
    },
    "trailblazeNodeTree": {
        "nodeId": 34,
        "children": [
            {
                "nodeId": 1,
                "ref": "c88",
                "bounds": {
                    "left": 300,
                    "top": 203,
                    "right": 1140,
                    "bottom": 296
                },
                "driverDetail": {
                    "class": "androidAccessibility",
                    "className": "android.widget.TextView",
                    "resourceId": "android:id/alertTitle",
                    "text": "Ringtones",
                    "packageName": "com.android.soundpicker",
                    "drawingOrder": 2,
                    "maxTextLength": -1,
                    "actions": [
                        "ACTION_SELECT",
                        "ACTION_CLEAR_SELECTION",
                        "ACTION_64",
                        "ACTION_256",
                        "ACTION_512",
                        "ACTION_SET_SELECTION",
                        "ACTION_SHOW_ON_SCREEN"
                    ]
                }
            },
            {
                "nodeId": 25,
                "children": [
                    {
                        "nodeId": 5,
                        "ref": "t692",
                        "bounds": {
                            "left": 216,
                            "top": 324,
                            "right": 1224,
                            "bottom": 492
                        },
                        "driverDetail": {
                            "class": "androidAccessibility",
                            "className": "android.widget.CheckedTextView",
                            "resourceId": "android:id/text1",
                            "text": "Default ringtone",
                            "isClickable": true,
                            "isCheckable": true,
                            "isChecked": true,
                            "isHeading": true,
                            "isMultiLine": true,
                            "collectionItemInfo": {
                                "rowIndex": 0,
                                "rowSpan": 1,
                                "columnIndex": 0,
                                "columnSpan": 1,
                                "isHeading": true
                            },
                            "packageName": "com.android.soundpicker",
                            "isLongClickable": true,
                            "drawingOrder": 1,
                            "maxTextLength": -1,
                            "actions": [
                                "ACTION_SELECT",
                                "ACTION_CLEAR_SELECTION",
                                "ACTION_CLICK",
                                "ACTION_LONG_CLICK",
                                "ACTION_64",
                                "ACTION_256",
                                "ACTION_512",
                                "ACTION_SET_SELECTION",
                                "ACTION_SHOW_ON_SCREEN"
                            ]
                        }
                    },
                    {
                        "nodeId": 6,
                        "ref": "c522",
                        "bounds": {
                            "left": 216,
                            "top": 492,
                            "right": 1224,
                            "bottom": 660
                        },
                        "driverDetail": {
                            "class": "androidAccessibility",
                            "className": "android.widget.CheckedTextView",
                            "resourceId": "android:id/text1",
                            "text": "None",
                            "isClickable": true,
                            "isCheckable": true,
                            "isHeading": true,
                            "isMultiLine": true,
                            "collectionItemInfo": {
                                "rowIndex": 1,
                                "rowSpan": 1,
                                "columnIndex": 0,
                                "columnSpan": 1,
                                "isHeading": true
                            },
                            "packageName": "com.android.soundpicker",
                            "isLongClickable": true,
                            "drawingOrder": 2,
                            "maxTextLength": -1,
                            "actions": [
                                "ACTION_SELECT",
                                "ACTION_CLEAR_SELECTION",
                                "ACTION_CLICK",
                                "ACTION_LONG_CLICK",
                                "ACTION_64",
                                "ACTION_256",
                                "ACTION_512",
                                "ACTION_SET_SELECTION",
                                "ACTION_SHOW_ON_SCREEN"
                            ]
                        }
                    },
                    {
                        "nodeId": 8,
                        "ref": "t393",
                        "children": [
                            {
                                "nodeId": 7,
                                "ref": "o558",
                                "bounds": {
                                    "left": 216,
                                    "top": 660,
                                    "right": 1224,
                                    "bottom": 828
                                },
                                "driverDetail": {
                                    "class": "androidAccessibility",
                                    "className": "android.widget.CheckedTextView",
                                    "resourceId": "com.android.soundpicker:id/checked_text_view",
                                    "text": "Andromeda",
                                    "isCheckable": true,
                                    "isMultiLine": true,
                                    "packageName": "com.android.soundpicker",
                                    "drawingOrder": 1,
                                    "maxTextLength": -1,
                                    "actions": [
                                        "ACTION_SELECT",
                                        "ACTION_CLEAR_SELECTION",
                                        "ACTION_64",
                                        "ACTION_256",
                                        "ACTION_512",
                                        "ACTION_SET_SELECTION",
                                        "ACTION_SHOW_ON_SCREEN"
                                    ]
                                }
                            }
                        ],
                        "bounds": {
                            "left": 216,
                            "top": 660,
                            "right": 1224,
                            "bottom": 828
                        },
                        "driverDetail": {
                            "class": "androidAccessibility",
                            "className": "android.widget.RelativeLayout",
                            "isClickable": true,
                            "collectionItemInfo": {
                                "rowIndex": 2,
                                "rowSpan": 1,
                                "columnIndex": 0,
                                "columnSpan": 1,
                                "isHeading": false
                            },
                            "packageName": "com.android.soundpicker",
                            "isLongClickable": true,
                            "drawingOrder": 3,
                            "maxTextLength": -1,
                            "actions": [
                                "ACTION_SELECT",
                                "ACTION_CLEAR_SELECTION",
                                "ACTION_CLICK",
                                "ACTION_LONG_CLICK",
                                "ACTION_64",
                                "ACTION_SHOW_ON_SCREEN"
                            ]
                        }
                    },
                    {
                        "nodeId": 10,
                        "ref": "y370",
                        "children": [
                            {
                                "nodeId": 9,
                                "ref": "t803",
                                "bounds": {
                                    "left": 216,
                                    "top": 828,
                                    "right": 1224,
                                    "bottom": 996
                                },
                                "driverDetail": {
                                    "class": "androidAccessibility",
                                    "className": "android.widget.CheckedTextView",
                                    "resourceId": "com.android.soundpicker:id/checked_text_view",
                                    "text": "Aquila",
                                    "isCheckable": true,
                                    "isMultiLine": true,
                                    "packageName": "com.android.soundpicker",
                                    "drawingOrder": 1,
                                    "maxTextLength": -1,
                                    "actions": [
                                        "ACTION_SELECT",
                                        "ACTION_CLEAR_SELECTION",
                                        "ACTION_64",
                                        "ACTION_256",
                                        "ACTION_512",
                                        "ACTION_SET_SELECTION",
                                        "ACTION_SHOW_ON_SCREEN"
                                    ]
                                }
                            }
                        ],
                        "bounds": {
                            "left": 216,
                            "top": 828,
                            "right": 1224,
                            "bottom": 996
                        },
                        "driverDetail": {
                            "class": "androidAccessibility",
                            "className": "android.widget.RelativeLayout",
                            "isClickable": true,
                            "collectionItemInfo": {
                                "rowIndex": 3,
                                "rowSpan": 1,
                                "columnIndex": 0,
                                "columnSpan": 1,
                                "isHeading": false
                            },
                            "packageName": "com.android.soundpicker",
                            "isLongClickable": true,
                            "drawingOrder": 4,
                            "maxTextLength": -1,
                            "actions": [
                                "ACTION_SELECT",
                                "ACTION_CLEAR_SELECTION",
                                "ACTION_CLICK",
                                "ACTION_LONG_CLICK",
                                "ACTION_64",
                                "ACTION_SHOW_ON_SCREEN"
                            ]
                        }
                    },
                    {
                        "nodeId": 12,
                        "ref": "y799",
                        "children": [
                            {
                                "nodeId": 11,
                                "ref": "d43",
                                "bounds": {
                                    "left": 216,
                                    "top": 996,
                                    "right": 1224,
                                    "bottom": 1164
                                },
                                "driverDetail": {
                                    "class": "androidAccessibility",
                                    "className": "android.widget.CheckedTextView",
                                    "resourceId": "com.android.soundpicker:id/checked_text_view",
                                    "text": "Argo Navis",
                                    "isCheckable": true,
                                    "isMultiLine": true,
                                    "packageName": "com.android.soundpicker",
                                    "drawingOrder": 1,
                                    "maxTextLength": -1,
                                    "actions": [
                                        "ACTION_SELECT",
                                        "ACTION_CLEAR_SELECTION",
                                        "ACTION_64",
                                        "ACTION_256",
                                        "ACTION_512",
                                        "ACTION_SET_SELECTION",
                                        "ACTION_SHOW_ON_SCREEN"
                                    ]
                                }
                            }
                        ],
                        "bounds": {
                            "left": 216,
                            "top": 996,
                            "right": 1224,
                            "bottom": 1164
                        },
                        "driverDetail": {
                            "class": "androidAccessibility",
                            "className": "android.widget.RelativeLayout",
                            "isClickable": true,
                            "collectionItemInfo": {
                                "rowIndex": 4,
                                "rowSpan": 1,
                                "columnIndex": 0,
                                "columnSpan": 1,
                                "isHeading": false
                            },
                            "packageName": "com.android.soundpicker",
                            "isLongClickable": true,
                            "drawingOrder": 5,
                            "maxTextLength": -1,
                            "actions": [
                                "ACTION_SELECT",
                                "ACTION_CLEAR_SELECTION",
                                "ACTION_CLICK",
                                "ACTION_LONG_CLICK",
                                "ACTION_64",
                                "ACTION_SHOW_ON_SCREEN"
                            ]
                        }
                    },
                    {
                        "nodeId": 14,
                        "ref": "p568",
                        "children": [
                            {
                                "nodeId": 13,
                                "ref": "q306",
                                "bounds": {
                                    "left": 216,
                                    "top": 1164,
                                    "right": 1224,
                                    "bottom": 1332
                                },
                                "driverDetail": {
                                    "class": "androidAccessibility",
                                    "className": "android.widget.CheckedTextView",
                                    "resourceId": "com.android.soundpicker:id/checked_text_view",
                                    "text": "Atria",
                                    "isCheckable": true,
                                    "isMultiLine": true,
                                    "packageName": "com.android.soundpicker",
                                    "drawingOrder": 1,
                                    "maxTextLength": -1,
                                    "actions": [
                                        "ACTION_SELECT",
                                        "ACTION_CLEAR_SELECTION",
                                        "ACTION_64",
                                        "ACTION_256",
                                        "ACTION_512",
                                        "ACTION_SET_SELECTION",
                                        "ACTION_SHOW_ON_SCREEN"
                                    ]
                                }
                            }
                        ],
                        "bounds": {
                            "left": 216,
                            "top": 1164,
                            "right": 1224,
                            "bottom": 1332
                        },
                        "driverDetail": {
                            "class": "androidAccessibility",
                            "className": "android.widget.RelativeLayout",
                            "isClickable": true,
                            "collectionItemInfo": {
                                "rowIndex": 5,
                                "rowSpan": 1,
                                "columnIndex": 0,
                                "columnSpan": 1,
                                "isHeading": false
                            },
                            "packageName": "com.android.soundpicker",
                            "isLongClickable": true,
                            "drawingOrder": 6,
                            "maxTextLength": -1,
                            "actions": [
                                "ACTION_SELECT",
                                "ACTION_CLEAR_SELECTION",
                                "ACTION_CLICK",
                                "ACTION_LONG_CLICK",
                                "ACTION_64",
                                "ACTION_SHOW_ON_SCREEN"
                            ]
                        }
                    },
                    {
                        "nodeId": 16,
                        "ref": "e450",
                        "children": [
                            {
                                "nodeId": 15,
                                "ref": "j285",
                                "bounds": {
                                    "left": 216,
                                    "top": 1332,
                                    "right": 1224,
                                    "bottom": 1500
                                },
                                "driverDetail": {
                                    "class": "androidAccessibility",
                                    "className": "android.widget.CheckedTextView",
                                    "resourceId": "com.android.soundpicker:id/checked_text_view",
                                    "text": "Backroad",
                                    "isCheckable": true,
                                    "isMultiLine": true,
                                    "packageName": "com.android.soundpicker",
                                    "drawingOrder": 1,
                                    "maxTextLength": -1,
                                    "actions": [
                                        "ACTION_SELECT",
                                        "ACTION_CLEAR_SELECTION",
                                        "ACTION_64",
                                        "ACTION_256",
                                        "ACTION_512",
                                        "ACTION_SET_SELECTION",
                                        "ACTION_SHOW_ON_SCREEN"
                                    ]
                                }
                            }
                        ],
                        "bounds": {
                            "left": 216,
                            "top": 1332,
                            "right": 1224,
                            "bottom": 1500
                        },
                        "driverDetail": {
                            "class": "androidAccessibility",
                            "className": "android.widget.RelativeLayout",
                            "isClickable": true,
                            "collectionItemInfo": {
                                "rowIndex": 6,
                                "rowSpan": 1,
                                "columnIndex": 0,
                                "columnSpan": 1,
                                "isHeading": false
                            },
                            "packageName": "com.android.soundpicker",
                            "isLongClickable": true,
                            "drawingOrder": 7,
                            "maxTextLength": -1,
                            "actions": [
                                "ACTION_SELECT",
                                "ACTION_CLEAR_SELECTION",
                                "ACTION_CLICK",
                                "ACTION_LONG_CLICK",
                                "ACTION_64",
                                "ACTION_SHOW_ON_SCREEN"
                            ]
                        }
                    },
                    {
                        "nodeId": 18,
                        "ref": "r233",
                        "children": [
                            {
                                "nodeId": 17,
                                "ref": "q380",
                                "bounds": {
                                    "left": 216,
                                    "top": 1500,
                                    "right": 1224,
                                    "bottom": 1668
                                },
                                "driverDetail": {
                                    "class": "androidAccessibility",
                                    "className": "android.widget.CheckedTextView",
                                    "resourceId": "com.android.soundpicker:id/checked_text_view",
                                    "text": "Beat Plucker",
                                    "isCheckable": true,
                                    "isMultiLine": true,
                                    "packageName": "com.android.soundpicker",
                                    "drawingOrder": 1,
                                    "maxTextLength": -1,
                                    "actions": [
                                        "ACTION_SELECT",
                                        "ACTION_CLEAR_SELECTION",
                                        "ACTION_64",
                                        "ACTION_256",
                                        "ACTION_512",
                                        "ACTION_SET_SELECTION",
                                        "ACTION_SHOW_ON_SCREEN"
                                    ]
                                }
                            }
                        ],
                        "bounds": {
                            "left": 216,
                            "top": 1500,
                            "right": 1224,
                            "bottom": 1668
                        },
                        "driverDetail": {
                            "class": "androidAccessibility",
                            "className": "android.widget.RelativeLayout",
                            "isClickable": true,
                            "collectionItemInfo": {
                                "rowIndex": 7,
                                "rowSpan": 1,
                                "columnIndex": 0,
                                "columnSpan": 1,
                                "isHeading": false
                            },
                            "packageName": "com.android.soundpicker",
                            "isLongClickable": true,
                            "drawingOrder": 8,
                            "maxTextLength": -1,
                            "actions": [
                                "ACTION_SELECT",
                                "ACTION_CLEAR_SELECTION",
                                "ACTION_CLICK",
                                "ACTION_LONG_CLICK",
                                "ACTION_64",
                                "ACTION_SHOW_ON_SCREEN"
                            ]
                        }
                    },
                    {
                        "nodeId": 20,
                        "ref": "r837",
                        "children": [
                            {
                                "nodeId": 19,
                                "ref": "m594",
                                "bounds": {
                                    "left": 216,
                                    "top": 1668,
                                    "right": 1224,
                                    "bottom": 1836
                                },
                                "driverDetail": {
                                    "class": "androidAccessibility",
                                    "className": "android.widget.CheckedTextView",
                                    "resourceId": "com.android.soundpicker:id/checked_text_view",
                                    "text": "Bell Phone",
                                    "isCheckable": true,
                                    "isMultiLine": true,
                                    "packageName": "com.android.soundpicker",
                                    "drawingOrder": 1,
                                    "maxTextLength": -1,
                                    "actions": [
                                        "ACTION_SELECT",
                                        "ACTION_CLEAR_SELECTION",
                                        "ACTION_64",
                                        "ACTION_256",
                                        "ACTION_512",
                                        "ACTION_SET_SELECTION",
                                        "ACTION_SHOW_ON_SCREEN"
                                    ]
                                }
                            }
                        ],
                        "bounds": {
                            "left": 216,
                            "top": 1668,
                            "right": 1224,
                            "bottom": 1836
                        },
                        "driverDetail": {
                            "class": "androidAccessibility",
                            "className": "android.widget.RelativeLayout",
                            "isClickable": true,
                            "collectionItemInfo": {
                                "rowIndex": 8,
                                "rowSpan": 1,
                                "columnIndex": 0,
                                "columnSpan": 1,
                                "isHeading": false
                            },
                            "packageName": "com.android.soundpicker",
                            "isLongClickable": true,
                            "drawingOrder": 9,
                            "maxTextLength": -1,
                            "actions": [
                                "ACTION_SELECT",
                                "ACTION_CLEAR_SELECTION",
                                "ACTION_CLICK",
                                "ACTION_LONG_CLICK",
                                "ACTION_64",
                                "ACTION_SHOW_ON_SCREEN"
                            ]
                        }
                    },
                    {
                        "nodeId": 22,
                        "ref": "u146",
                        "children": [
                            {
                                "nodeId": 21,
                                "ref": "j582",
                                "bounds": {
                                    "left": 216,
                                    "top": 1836,
                                    "right": 1224,
                                    "bottom": 2004
                                },
                                "driverDetail": {
                                    "class": "androidAccessibility",
                                    "className": "android.widget.CheckedTextView",
                                    "resourceId": "com.android.soundpicker:id/checked_text_view",
                                    "text": "Bentley Dubs",
                                    "isCheckable": true,
                                    "isMultiLine": true,
                                    "packageName": "com.android.soundpicker",
                                    "drawingOrder": 1,
                                    "maxTextLength": -1,
                                    "actions": [
                                        "ACTION_SELECT",
                                        "ACTION_CLEAR_SELECTION",
                                        "ACTION_64",
                                        "ACTION_256",
                                        "ACTION_512",
                                        "ACTION_SET_SELECTION",
                                        "ACTION_SHOW_ON_SCREEN"
                                    ]
                                }
                            }
                        ],
                        "bounds": {
                            "left": 216,
                            "top": 1836,
                            "right": 1224,
                            "bottom": 2004
                        },
                        "driverDetail": {
                            "class": "androidAccessibility",
                            "className": "android.widget.RelativeLayout",
                            "isClickable": true,
                            "collectionItemInfo": {
                                "rowIndex": 9,
                                "rowSpan": 1,
                                "columnIndex": 0,
                                "columnSpan": 1,
                                "isHeading": false
                            },
                            "packageName": "com.android.soundpicker",
                            "isLongClickable": true,
                            "drawingOrder": 10,
                            "maxTextLength": -1,
                            "actions": [
                                "ACTION_SELECT",
                                "ACTION_CLEAR_SELECTION",
                                "ACTION_CLICK",
                                "ACTION_LONG_CLICK",
                                "ACTION_64",
                                "ACTION_SHOW_ON_SCREEN"
                            ]
                        }
                    },
                    {
                        "nodeId": 24,
                        "ref": "u825",
                        "children": [
                            {
                                "nodeId": 23,
                                "ref": "p990",
                                "bounds": {
                                    "left": 216,
                                    "top": 2004,
                                    "right": 1224,
                                    "bottom": 2140
                                },
                                "driverDetail": {
                                    "class": "androidAccessibility",
                                    "className": "android.widget.CheckedTextView",
                                    "resourceId": "com.android.soundpicker:id/checked_text_view",
                                    "text": "Big Easy",
                                    "isCheckable": true,
                                    "isMultiLine": true,
                                    "packageName": "com.android.soundpicker",
                                    "drawingOrder": 1,
                                    "maxTextLength": -1,
                                    "actions": [
                                        "ACTION_SELECT",
                                        "ACTION_CLEAR_SELECTION",
                                        "ACTION_64",
                                        "ACTION_256",
                                        "ACTION_512",
                                        "ACTION_SET_SELECTION",
                                        "ACTION_SHOW_ON_SCREEN"
                                    ]
                                }
                            }
                        ],
                        "bounds": {
                            "left": 216,
                            "top": 2004,
                            "right": 1224,
                            "bottom": 2140
                        },
                        "driverDetail": {
                            "class": "androidAccessibility",
                            "className": "android.widget.RelativeLayout",
                            "isClickable": true,
                            "collectionItemInfo": {
                                "rowIndex": 10,
                                "rowSpan": 1,
                                "columnIndex": 0,
                                "columnSpan": 1,
                                "isHeading": false
                            },
                            "packageName": "com.android.soundpicker",
                            "isLongClickable": true,
                            "drawingOrder": 11,
                            "maxTextLength": -1,
                            "actions": [
                                "ACTION_SELECT",
                                "ACTION_CLEAR_SELECTION",
                                "ACTION_CLICK",
                                "ACTION_LONG_CLICK",
                                "ACTION_64",
                                "ACTION_SHOW_ON_SCREEN"
                            ]
                        }
                    }
                ],
                "bounds": {
                    "left": 216,
                    "top": 324,
                    "right": 1224,
                    "bottom": 2140
                },
                "driverDetail": {
                    "class": "androidAccessibility",
                    "className": "android.widget.ListView",
                    "resourceId": "android:id/select_dialog_listview",
                    "isFocused": true,
                    "isScrollable": true,
                    "packageName": "com.android.soundpicker",
                    "isLongClickable": true,
                    "isFocusable": true,
                    "drawingOrder": 1,
                    "maxTextLength": -1,
                    "actions": [
                        "ACTION_CLEAR_FOCUS",
                        "ACTION_SELECT",
                        "ACTION_CLEAR_SELECTION",
                        "ACTION_LONG_CLICK",
                        "ACTION_64",
                        "ACTION_SCROLL_FORWARD",
                        "ACTION_SHOW_ON_SCREEN",
                        "ACTION_16908343",
                        "ACTION_SCROLL_DOWN"
                    ],
                    "collectionInfo": {
                        "rowCount": -1,
                        "columnCount": -1,
                        "isHierarchical": false
                    }
                }
            },
            {
                "nodeId": 30,
                "children": [
                    {
                        "nodeId": 27,
                        "ref": "f607",
                        "bounds": {
                            "left": 689,
                            "top": 2154,
                            "right": 958,
                            "bottom": 2322
                        },
                        "driverDetail": {
                            "class": "androidAccessibility",
                            "className": "android.widget.Button",
                            "resourceId": "android:id/button2",
                            "text": "CANCEL",
                            "isClickable": true,
                            "isMultiLine": true,
                            "packageName": "com.android.soundpicker",
                            "isFocusable": true,
                            "drawingOrder": 3,
                            "maxTextLength": -1,
                            "actions": [
                                "ACTION_FOCUS",
                                "ACTION_SELECT",
                                "ACTION_CLEAR_SELECTION",
                                "ACTION_CLICK",
                                "ACTION_64",
                                "ACTION_256",
                                "ACTION_512",
                                "ACTION_SET_SELECTION",
                                "ACTION_SHOW_ON_SCREEN"
                            ]
                        }
                    },
                    {
                        "nodeId": 28,
                        "ref": "d820",
                        "bounds": {
                            "left": 958,
                            "top": 2154,
                            "right": 1182,
                            "bottom": 2322
                        },
                        "driverDetail": {
                            "class": "androidAccessibility",
                            "className": "android.widget.Button",
                            "resourceId": "android:id/button1",
                            "text": "OK",
                            "isClickable": true,
                            "isMultiLine": true,
                            "packageName": "com.android.soundpicker",
                            "isFocusable": true,
                            "drawingOrder": 4,
                            "maxTextLength": -1,
                            "actions": [
                                "ACTION_FOCUS",
                                "ACTION_SELECT",
                                "ACTION_CLEAR_SELECTION",
                                "ACTION_CLICK",
                                "ACTION_64",
                                "ACTION_256",
                                "ACTION_512",
                                "ACTION_SET_SELECTION",
                                "ACTION_SHOW_ON_SCREEN"
                            ]
                        }
                    }
                ],
                "bounds": {
                    "left": 216,
                    "top": 2140,
                    "right": 1224,
                    "bottom": 2336
                },
                "driverDetail": {
                    "class": "androidAccessibility",
                    "className": "android.widget.ScrollView",
                    "resourceId": "android:id/buttonPanel",
                    "packageName": "com.android.soundpicker",
                    "isFocusable": true,
                    "drawingOrder": 4,
                    "maxTextLength": -1,
                    "actions": [
                        "ACTION_FOCUS",
                        "ACTION_SELECT",
                        "ACTION_CLEAR_SELECTION",
                        "ACTION_64",
                        "ACTION_SHOW_ON_SCREEN"
                    ]
                }
            }
        ],
        "bounds": {
            "left": 160,
            "top": 84,
            "right": 1280,
            "bottom": 2392
        },
        "driverDetail": {
            "class": "androidAccessibility",
            "className": "android.widget.FrameLayout",
            "packageName": "com.android.soundpicker",
            "maxTextLength": -1,
            "actions": [
                "ACTION_SELECT",
                "ACTION_CLEAR_SELECTION",
                "ACTION_64",
                "ACTION_SHOW_ON_SCREEN"
            ]
        }
    }
}